CHANGELOG.rst
LICENSE
MANIFEST.in
README.rst
setup.cfg
setup.py
cryptnoxcard/__init__.py
cryptnoxcard/card.py
cryptnoxcard/config.py
cryptnoxcard/enums.py
cryptnoxcard/erc_token.py
cryptnoxcard/interactive_cli.py
cryptnoxcard.egg-info/PKG-INFO
cryptnoxcard.egg-info/SOURCES.txt
cryptnoxcard.egg-info/dependency_links.txt
cryptnoxcard.egg-info/entry_points.txt
cryptnoxcard.egg-info/not-zip-safe
cryptnoxcard.egg-info/requires.txt
cryptnoxcard.egg-info/top_level.txt
cryptnoxcard/command/__init__.py
cryptnoxcard/command/btc.py
cryptnoxcard/command/card_configuration.py
cryptnoxcard/command/cards.py
cryptnoxcard/command/change_pin.py
cryptnoxcard/command/change_puk.py
cryptnoxcard/command/command.py
cryptnoxcard/command/config.py
cryptnoxcard/command/eosio.py
cryptnoxcard/command/eth.py
cryptnoxcard/command/history.py
cryptnoxcard/command/reset.py
cryptnoxcard/command/seed.py
cryptnoxcard/command/unknown.py
cryptnoxcard/command/unlock_pin.py
cryptnoxcard/command/user_key.py
cryptnoxcard/command/card/__init__.py
cryptnoxcard/command/card/factory.py
cryptnoxcard/command/card/info.py
cryptnoxcard/command/card/initialize.py
cryptnoxcard/command/card/interactive.py
cryptnoxcard/command/card/options.py
cryptnoxcard/command/erc_token/__init__.py
cryptnoxcard/command/erc_token/contract.py
cryptnoxcard/command/erc_token/factory.py
cryptnoxcard/command/erc_token/info.py
cryptnoxcard/command/erc_token/initialize.py
cryptnoxcard/command/erc_token/interactive.py
cryptnoxcard/command/erc_token/options.py
cryptnoxcard/command/erc_token/transfer.py
cryptnoxcard/command/helper/__init__.py
cryptnoxcard/command/helper/backup.py
cryptnoxcard/command/helper/cards.py
cryptnoxcard/command/helper/config.py
cryptnoxcard/command/helper/helper_methods.py
cryptnoxcard/command/helper/notification.py
cryptnoxcard/command/helper/security.py
cryptnoxcard/command/helper/seed_backup.py
cryptnoxcard/command/helper/ui.py
cryptnoxcard/command/options/__init__.py
cryptnoxcard/command/options/common.py
cryptnoxcard/command/options/eosio.py
cryptnoxcard/command/options/eth.py
cryptnoxcard/command/options/options.py
cryptnoxcard/command/user_keys/__init__.py
cryptnoxcard/command/user_keys/authentication.py
cryptnoxcard/command/user_keys/user_key_base.py
