Metadata-Version: 2.1
Name: cryptnoxcard
Version: 2.1.0
Summary: UNKNOWN
Home-page: https://www.cryptnox.com/
Author: Cryptnox SA
Author-email: info@cryptnox.ch
License: GPLv3+
Project-URL: Source Code, https://github.com/Cryptnox-Software/cryptnoxcard
Keywords: python,cryptography,bitcoin,ethereum,cleos,cryptocurrency,wallet
Platform: any
Classifier: Development Status :: 4 - Beta
Classifier: Environment :: Console
Classifier: License :: OSI Approved :: GNU General Public License v3 or later (GPLv3+)
Classifier: License :: Other/Proprietary License
Classifier: Operating System :: OS Independent
Classifier: Programming Language :: Python :: 3 :: Only
Classifier: Programming Language :: Python :: 3.6
Classifier: Programming Language :: Python :: 3.7
Classifier: Programming Language :: Python :: 3.8
Classifier: Programming Language :: Python :: 3.9
Classifier: Topic :: Security :: Cryptography
Requires-Python: <3.10,>=3.6
License-File: LICENSE
